cv2.cpython-312-x86_64-linux-gnu.so
opencv_ffmpeg_gstreamer-4.5.3.dist-info/top_level.txt
opencv_ffmpeg_gstreamer-4.5.3.dist-info/RECORD
opencv_ffmpeg_gstreamer-4.5.3.dist-info/METADATA
opencv_ffmpeg_gstreamer-4.5.3.dist-info/WHEEL
