Metadata-Version: 2.1
Name: opencv-ffmpeg-gstreamer
Version: 4.5.3
Summary: Custom OpenCV build with FFmpeg and GStreamer support
Home-page: https://github.com/herambgvd/opencv-ffmpeg-gstreamer
Author: Heramb Mishra
Author-email: heramb1008@gmail.com
Classifier: Programming Language :: Python :: 3
Classifier: License :: OSI Approved :: MIT License
Classifier: Operating System :: OS Independent
Requires-Python: >=3.6
